kubespec/__init__.py
kubespec/context.py
kubespec/types.py
kubespec/bitnami/__init__.py
kubespec/bitnami/v1alpha1.py
kubespec/certmanager/__init__.py
kubespec/certmanager/v1alpha3.py
kubespec/certmanager/acme/__init__.py
kubespec/certmanager/acme/v1alpha3.py
kubespec/certmanager/acme/webhook/__init__.py
kubespec/certmanager/acme/webhook/v1alpha1.py
kubespec/coreos/__init__.py
kubespec/coreos/monitoring/__init__.py
kubespec/coreos/monitoring/v1.py
kubespec/k8s/__init__.py
kubespec/k8s/base.py
kubespec/k8s/resource.py
kubespec/k8s/runtime.py
kubespec/k8s/v1.py
kubespec/k8s/admission/__init__.py
kubespec/k8s/admission/v1.py
kubespec/k8s/admission/v1beta1.py
kubespec/k8s/admissionregistration/__init__.py
kubespec/k8s/admissionregistration/v1.py
kubespec/k8s/admissionregistration/v1beta1.py
kubespec/k8s/apiextensions/__init__.py
kubespec/k8s/apiextensions/v1.py
kubespec/k8s/apiextensions/v1beta1.py
kubespec/k8s/apiregistration/__init__.py
kubespec/k8s/apiregistration/v1.py
kubespec/k8s/apiregistration/v1beta1.py
kubespec/k8s/apiserver/__init__.py
kubespec/k8s/apiserver/v1alpha1.py
kubespec/k8s/apiserver/flowcontrol/__init__.py
kubespec/k8s/apiserver/flowcontrol/v1alpha1.py
kubespec/k8s/apps/__init__.py
kubespec/k8s/apps/v1.py
kubespec/k8s/apps/v1beta1.py
kubespec/k8s/apps/v1beta2.py
kubespec/k8s/audit/__init__.py
kubespec/k8s/audit/v1.py
kubespec/k8s/audit/v1beta1.py
kubespec/k8s/auditregistration/__init__.py
kubespec/k8s/auditregistration/v1alpha1.py
kubespec/k8s/authentication/__init__.py
kubespec/k8s/authentication/v1.py
kubespec/k8s/authentication/v1beta1.py
kubespec/k8s/authorization/__init__.py
kubespec/k8s/authorization/v1.py
kubespec/k8s/authorization/v1beta1.py
kubespec/k8s/authorization/abac/__init__.py
kubespec/k8s/authorization/abac/v0.py
kubespec/k8s/authorization/abac/v1beta1.py
kubespec/k8s/authorization/rbac/__init__.py
kubespec/k8s/authorization/rbac/v1.py
kubespec/k8s/authorization/rbac/v1beta1.py
kubespec/k8s/autoscaling/__init__.py
kubespec-0.1.dev20200203.dist-info/LICENSE
kubespec-0.1.dev20200203.dist-info/METADATA
kubespec-0.1.dev20200203.dist-info/WHEEL
kubespec-0.1.dev20200203.dist-info/top_level.txt
kubespec-0.1.dev20200203.dist-info/RECORD
