Metadata-Version: 2.1
Name: kubespec
Version: 0.1.dev20200203
Summary: Kubespec is a set of foundational libraries for expressing Kubernetes resource specifications as code.
Home-page: https://github.com/machinezone/kubespec
Author: Andy Bursavich
Author-email: abursavich@mz.com
License: BSD 3
Platform: UNKNOWN
Classifier: Development Status :: 3 - Alpha
Classifier: Intended Audience :: Developers
Classifier: Intended Audience :: Information Technology
Classifier: Intended Audience :: System Administrators
Classifier: License :: OSI Approved :: BSD License
Classifier: Operating System :: OS Independent
Classifier: Programming Language :: Python
Classifier: Programming Language :: Python :: 3
Classifier: Programming Language :: Python :: 3.7
Classifier: Programming Language :: Python :: 3.8
Classifier: Topic :: Software Development
Classifier: Topic :: Software Development :: Libraries
Classifier: Topic :: System
Classifier: Topic :: System :: Systems Administration
Classifier: Topic :: Utilities
Classifier: Typing :: Typed
Requires-Python: >=3.7
Requires-Dist: pytz (>=2019.3)
Requires-Dist: typeguard (>=2.7.1)
